[{"Name":"Panaderia Suiza","Location":"Av. Costanera 194","Rubro":{"Description":"Catering, Sanitarios, etc","Name":"SERVICIOS"},"ID":"12312321"},{"Name":"Restor\u00E1n Garc\u00EDa","Location":"Av. Alfredo Arocena 1587","Rubro":{"Description":"autos y motos ruta 5","Name":"TRANSPORTE"},"ID":"1234"},{"Name":"DESEM","Location":"Blvr. Espa\u00F1a 2183","Rubro":{"Description":"Emprender","Name":"Emprendedores"},"ID":"4134134"},{"Name":"Asociaci\u00F3n Empretec Uruguay","Location":"Av. Italia 6101 ","Rubro":{"Description":"Emprender","Name":"Emprendedores"},"ID":"41123213"}]